datu_sdk/__init__.py
datu_sdk/shark/__init__.py
datu_sdk/shark/annotation_task.py
datu_sdk/shark/base_api.py
datu_sdk/shark/client.py
datu_sdk/shark/project.py
datu_sdk/shark/trainer.py
datu_sdk/shark/common/__init__.py
datu_sdk/shark/common/enums.py
datu_sdk/shark/common/logging.py
datu_sdk-0.0.1.dist-info/LICENSE
datu_sdk-0.0.1.dist-info/METADATA
datu_sdk-0.0.1.dist-info/WHEEL
datu_sdk-0.0.1.dist-info/top_level.txt
datu_sdk-0.0.1.dist-info/RECORD
