Metadata-Version: 2.1
Name: datu-sdk
Version: 0.0.1
Summary: SDK to use Datu service
Home-page: https://github.com/datu-ai/datu-sdk
Author: Fisher Yu
Author-email: f@datu.ai
License: UNKNOWN
Platform: UNKNOWN
Classifier: Programming Language :: Python :: 3
Classifier: License :: OSI Approved :: Apache Software License
Classifier: Operating System :: OS Independent
Requires-Python: >=3.7
